README.rst
setup.py
peek_plugin_docdb/__init__.py
peek_plugin_docdb/plugin_package.json
peek_plugin_docdb.egg-info/PKG-INFO
peek_plugin_docdb.egg-info/SOURCES.txt
peek_plugin_docdb.egg-info/dependency_links.txt
peek_plugin_docdb.egg-info/requires.txt
peek_plugin_docdb.egg-info/top_level.txt
peek_plugin_docdb/_private/PluginNames.py
peek_plugin_docdb/_private/__init__.py
peek_plugin_docdb/_private/alembic.ini
peek_plugin_docdb/_private/admin-app/docDb.component.html
peek_plugin_docdb/_private/admin-app/docDb.component.ts
peek_plugin_docdb/_private/admin-app/docDb.module.ts
peek_plugin_docdb/_private/admin-app/edit-object-type-table/edit.component.html
peek_plugin_docdb/_private/admin-app/edit-object-type-table/edit.component.ts
peek_plugin_docdb/_private/admin-app/edit-property-table/edit.component.html
peek_plugin_docdb/_private/admin-app/edit-property-table/edit.component.ts
peek_plugin_docdb/_private/admin-app/edit-setting-table/edit.component.html
peek_plugin_docdb/_private/admin-app/edit-setting-table/edit.component.ts
peek_plugin_docdb/_private/admin-app/status/status.component.html
peek_plugin_docdb/_private/admin-app/status/status.component.ts
peek_plugin_docdb/_private/admin-app/view-document/view-document.html
peek_plugin_docdb/_private/admin-app/view-document/view-document.ts
peek_plugin_docdb/_private/agent/AgentEntryHook.py
peek_plugin_docdb/_private/agent/__init__.py
peek_plugin_docdb/_private/alembic/__init__.py
peek_plugin_docdb/_private/alembic/env.py
peek_plugin_docdb/_private/alembic/script.py.mako
peek_plugin_docdb/_private/alembic/versions/0b20ccfb7a6a_change_to_biginteger.py
peek_plugin_docdb/_private/alembic/versions/6c94c040e18c_added_showinheader.py
peek_plugin_docdb/_private/alembic/versions/931b88db3117_added_showon_fields.py
peek_plugin_docdb/_private/alembic/versions/__init__.py
peek_plugin_docdb/_private/alembic/versions/a423a783700f_increased_chunk_size.py
peek_plugin_docdb/_private/alembic/versions/c1d2d5475c64_initial_tables.py
peek_plugin_docdb/_private/both-app/docdb-popup.module.ts
peek_plugin_docdb/_private/both-app/components/index.ts
peek_plugin_docdb/_private/both-app/components/popup/index.ts
