Metadata-Version: 1.1
Name: peek-plugin-docdb
Version: 2.5.4
Summary: Peek Plugin DocDb - My first enhancement.
Home-page: https://bitbucket.org/synerty/peek-plugin-docdb
Author: Synerty
Author-email: contact@synerty.com
License: UNKNOWN
Download-URL: https://bitbucket.org/synerty/peek-plugin-docdb/get/2.5.4.zip
Keywords: Peek,Python,Platform,synerty
Platform: UNKNOWN
